memory_transformer_xl/__init__.py
memory_transformer_xl/autoregressive_wrapper.py
memory_transformer_xl/memory_transformer_xl.py
memory_transformer_xl-0.1.0.dist-info/LICENSE
memory_transformer_xl-0.1.0.dist-info/METADATA
memory_transformer_xl-0.1.0.dist-info/WHEEL
memory_transformer_xl-0.1.0.dist-info/top_level.txt
memory_transformer_xl-0.1.0.dist-info/RECORD
